main.py
mcp_stampit-0.1.7.dist-info/licenses/LICENSE
mcp_stampit-0.1.7.dist-info/METADATA
mcp_stampit-0.1.7.dist-info/WHEEL
mcp_stampit-0.1.7.dist-info/entry_points.txt
mcp_stampit-0.1.7.dist-info/top_level.txt
mcp_stampit-0.1.7.dist-info/RECORD
