Metadata-Version: 2.4
Name: mcp-stampit
Version: 0.1.7
Summary: A lightweight MCP component for adding text watermarks to pictures
Author-email: Liu Hao <liu.hao1443@gmail.com>
License-Expression: Apache-2.0
Project-URL: Homepage, https://github.com/LiuHao-1443/stampit
Project-URL: Bug Tracker, https://github.com/LiuHao-1443/stampit/issues
Requires-Python: >=3.13
License-File: LICENSE
Requires-Dist: fastmcp>=0.1.0
Requires-Dist: pillow>=10.0.0
Requires-Dist: requests>=2.31.0
Requires-Dist: pydantic>=2.0.0
Requires-Dist: pytest>=7.0.0
Dynamic: license-file
